specious
