Metadata-Version: 2.1
Name: specious
Version: 0.0.5
Summary: Just screenshot allure report and send.
Home-page: https://github.com/aquichita/specious
Author: aquichita
Author-email: chaochao.wu@outlook.com
License: UNKNOWN
Platform: UNKNOWN
Requires-Python: >=3.8
